ckanext_resourcedictionary-1.0.0-py3.8-nspkg.pth
ckanext/resourcedictionary/__init__.py
ckanext/resourcedictionary/plugin.py
ckanext/resourcedictionary/assets/webassets.yml
ckanext/resourcedictionary/assets/js/dictionary_form.js
ckanext/resourcedictionary/logic/__init__.py
ckanext/resourcedictionary/logic/action/__init__.py
ckanext/resourcedictionary/logic/action/create.py
ckanext/resourcedictionary/templates/ajax_snippets/dictionary_field.html
ckanext/resourcedictionary/templates/dictionary/dictionary.html
ckanext/resourcedictionary/templates/dictionary/snippets/delete_field_button.html
ckanext/resourcedictionary/templates/package/resource_edit_base.html
ckanext/resourcedictionary/tests/__init__.py
ckanext/resourcedictionary/views/__init__.py
ckanext/resourcedictionary/views/resource_dictionary.py
ckanext_resourcedictionary-1.0.0.dist-info/LICENSE
ckanext_resourcedictionary-1.0.0.dist-info/METADATA
ckanext_resourcedictionary-1.0.0.dist-info/WHEEL
ckanext_resourcedictionary-1.0.0.dist-info/entry_points.txt
ckanext_resourcedictionary-1.0.0.dist-info/namespace_packages.txt
ckanext_resourcedictionary-1.0.0.dist-info/top_level.txt
ckanext_resourcedictionary-1.0.0.dist-info/RECORD
