Metadata-Version: 2.1
Name: ckanext-resourcedictionary
Version: 1.0.0
Summary: Extends the default CKAN Data Dictionary functionality     by adding possibility to create data dictionary     before actual data is uploaded to datastore.
Home-page: https://github.com/keitaroinc/ckanext-resourcedictionary
Author: Keitaro Inc
Author-email: info@keitaro.com
License: AGPL
Keywords: CKAN data dictionary resource datastore
Platform: UNKNOWN
Classifier: Development Status :: 5 - Production/Stable
Classifier: License :: OSI Approved :: GNU Affero General Public License v3 or later (AGPLv3+)
Classifier: Programming Language :: Python :: 3.8
